dnsuptools/__init__.py
dnsuptools/dkimrecgen.py
dnsuptools/dnshelpers.py
dnsuptools/dnsupdate.py
dnsuptools/dnsuptools.py
dnsuptools/inwxwrapper.py
dnsuptools/passwords.py
dnsuptools/testdnsupdate.py
dnsuptools/testdnsuptools.py
dnsuptools/tlsarecgen.py
tests/__init__.py
tests/passwords.py
tests/test_dkimrecgen.py
tests/test_dnsupdate.py
tests/test_tlsarecgen.py
dnsuptools-0.0.23.post4.dist-info/LICENCE
dnsuptools-0.0.23.post4.dist-info/METADATA
dnsuptools-0.0.23.post4.dist-info/WHEEL
dnsuptools-0.0.23.post4.dist-info/top_level.txt
dnsuptools-0.0.23.post4.dist-info/RECORD
