Metadata-Version: 2.1
Name: dnsuptools
Version: 0.0.23.post4
Summary: Library interfaces to dns service api for query, update, add, delete comfortably.
Home-page: https://github.com/TheTesla/dnsuptools
Author: Stefan Helmert
Author-email: stefan.helmert@t-online.de
License: UNKNOWN
Platform: UNKNOWN
Classifier: Programming Language :: Python :: 3
Classifier: License :: OSI Approved :: MIT License
Classifier: Operating System :: OS Independent
Requires-Dist: dnspython
Requires-Dist: inwx-domrobot
Requires-Dist: pycurl
Requires-Dist: simpleloggerplus
